xps_export/__init__.py
xps_export/__main__.py
xps_export/xpsexport.py
xps_export-1.0.9.dist-info/METADATA
xps_export-1.0.9.dist-info/WHEEL
xps_export-1.0.9.dist-info/entry_points.txt
xps_export-1.0.9.dist-info/top_level.txt
xps_export-1.0.9.dist-info/RECORD
