Metadata-Version: 2.1
Name: xps-export
Version: 1.0.9
Summary: XPS-Export is a tool designed to facilitate the conversion of SPE, ANG, SXI, and PRO files from X-ray Photoelectron Spectroscopy (XPS) measurements into a format that is both human- and Python-readable. This streamlined conversion ensures easy access, readability, and visualization of measurement data for further analysis and interpretation.
Home-page: https://gitlab.tuwien.ac.at/iap/aip/anp/xps-export
Author: Richard van Nieuwenhoven, Johannes Prisslan, Kai Alexander Schwenzfeier, Markus Valtiner
Author-email: richard.nieuwenhoven@tuwien.ac.at, e12042169@student.tuwien.ac.at, schwenzfeier@iap.tuwien.ac.at, markus.valtiner@tuwien.ac.at
Project-URL: Homepage, https://gitlab.tuwien.ac.at/iap/aip/anp/xps-export
Keywords: xps spe ang sxi pro conversion
Classifier: Programming Language :: Python :: 3
Classifier: License :: OSI Approved :: MIT License
Classifier: Operating System :: OS Independent
Requires-Python: >=3.1
Requires-Dist: matplotlib>=3.5.1
Requires-Dist: NumPy<2.0
